[
  {
    "id": "3025770",
    "title": "Carte graphique GeForce RTX 5070 WINDFORCE OC SFF 12 Go (et d'autres modèles)",
    "price": 649,
    "price_before_discount": null,
    "discount": null,
    "url": "https://www.dealabs.com/bons-plans/carte-graphique-geforce-rtx-5070-windforce-oc-sff-12go-3025770",
    "photo_url": "https://static-pepper.dealabs.com/threads/raw/Sf5e5/3025770_1/re/1024x1024/qt/70/3025770_1.jpg",
    "hotness": 1207,
    "description": "Posté il y a 19 h.",
    "scrape_date": "2025-03-25T08:25:50.638Z"
  },
  {
    "id": "3026022",
    "title": "Licence Plex à vie - (via facturation Argentine)",
    "price": 34.2,
    "price_before_discount": 119.99,
    "discount": "-71",
    "url": "https://www.dealabs.com/bons-plans/plex-pass-3026022",
    "photo_url": "https://static-pepper.dealabs.com/threads/raw/oglv1/3026022_1/re/1024x1024/qt/70/3026022_1.jpg",
    "hotness": 1072,
    "description": "Posté il y a 11 h.",
    "scrape_date": "2025-03-25T08:25:50.638Z"
  },
  {
    "id": "3025752",
    "title": "Machine à crème glacée Ninja Creami NC300EU",
    "price": 129.99,
    "price_before_discount": 179,
    "discount": "-27",
    "url": "https://www.dealabs.com/bons-plans/rakuten-ninja-creami-standard-3025752",
    "photo_url": "https://static-pepper.dealabs.com/threads/raw/xvxJI/3025752_1/re/1024x1024/qt/70/3025752_1.jpg",
    "hotness": 985,
    "description": "Posté il y a 19 h.",
    "scrape_date": "2025-03-25T08:25:50.638Z"
  },
  {
    "id": "3025785",
    "title": "[Client +de 3 mois] 200€ offerts pour l'ouverture d'une assurance vie avec dépôt >2500€",
    "price": 0,
    "price_before_discount": null,
    "discount": null,
    "url": "https://www.dealabs.com/codes-promo/client-de-3-mois-200eur-offerts-pour-louverture-dune-assurance-vie-avec-depot-2500eur-3025785",
    "photo_url": "https://static-pepper.dealabs.com/threads/raw/YwxfM/3025785_1/re/1024x1024/qt/70/3025785_1.jpg",
    "hotness": 945,
    "description": "Posté il y a 18 h.",
    "scrape_date": "2025-03-25T08:25:50.638Z"
  },
  {
    "id": "3025781",
    "title": "[Client +de 3 mois] 100€ offerts pour un versement libre de 3000€ sur votre contrat d' assurance vie",
    "price": 0,
    "price_before_discount": null,
    "discount": null,
    "url": "https://www.dealabs.com/bons-plans/client-de-3-mois-100eur-offerts-pour-un-versement-libre-de-3000eur-3025781",
    "photo_url": "https://static-pepper.dealabs.com/threads/raw/IYRE6/3025781_1/re/1024x1024/qt/70/3025781_1.jpg",
    "hotness": 836,
    "description": "Posté il y a 19 h.",
    "scrape_date": "2025-03-25T08:25:50.638Z"
  }
]